NeuralBasics/__init__.py
NeuralBasics/network.py
NeuralBasics/test.py
NeuralBasics/utils.py
NeuralBasics/training/MNIST/big/train-images-idx3-ubyte.gz
NeuralBasics/training/MNIST/big/train-images.idx3-ubyte
NeuralBasics/training/MNIST/big/train-labels-idx1-ubyte.gz
NeuralBasics/training/MNIST/big/train-labels.idx1-ubyte
NeuralBasics/training/MNIST/small/t10k-images-idx3-ubyte
NeuralBasics/training/MNIST/small/t10k-images-idx3-ubyte.gz
NeuralBasics/training/MNIST/small/t10k-labels-idx1-ubyte
NeuralBasics/training/MNIST/small/t10k-labels-idx1-ubyte.gz
NeuralBasics-1.0.16.dist-info/METADATA
NeuralBasics-1.0.16.dist-info/WHEEL
NeuralBasics-1.0.16.dist-info/top_level.txt
NeuralBasics-1.0.16.dist-info/RECORD
