Metadata-Version: 2.1
Name: NeuralBasics
Version: 1.0.16
Summary: Neural network basics module. Number detection on images.
Author: Henry Cook
Author-email: Henry Cook <henryscookolaizola@gmail.com>
Project-URL: Homepage, https://github.com/HCook86/NeuralBasics
Project-URL: Bug Tracker, https://github.com/HCook86/NeuralBasics/issues
Classifier: Programming Language :: Python :: 3
Classifier: License :: OSI Approved :: MIT License
Classifier: Operating System :: OS Independent
Requires-Python: >=3.6
Requires-Dist: numpy
Requires-Dist: alive-progress
Requires-Dist: Pillow
Requires-Dist: matplotlib
Requires-Dist: idx2numpy
